Metadata-Version: 1.1
Name: django-indisposable
Version: 1.0.0
Summary: Disallow disposable email addresses in Django EmailField
Home-page: https://github.com/jonashaag/django-indisposable
Author: Jonas Haag
Author-email: jonas@lophus.org
License: UNKNOWN
Platform: UNKNOWN
Classifier: Development Status :: 5 - Production/Stable
Classifier: Topic :: Internet :: WWW/HTTP :: Dynamic Content
Classifier: Topic :: Internet :: WWW/HTTP :: WSGI :: Application
Classifier: Topic :: Software Development :: Version Control
Classifier: Environment :: Web Environment
Classifier: Intended Audience :: Developers
Classifier: License :: OSI Approved :: ISC License (ISCL)
Classifier: Programming Language :: Python
Classifier: Programming Language :: Python :: 2.7
Classifier: Programming Language :: Python :: 3
